strangeworks_ionq_extension/__init__.py
strangeworks_ionq_extension/extensions/__init__.py
strangeworks_ionq_extension/extensions/qiskit_ionq/__init__.py
strangeworks_ionq_extension/extensions/qiskit_ionq/_result.py
strangeworks_ionq_extension/extensions/qiskit_ionq/_retrieve.py
strangeworks_ionq_extension/extensions/qiskit_ionq/_submit.py
strangeworks_ionq_extension/extensions/qiskit_ionq/plugin.py
strangeworks_qiskit_ionq_extension-0.8.0rc1.dist-info/METADATA
strangeworks_qiskit_ionq_extension-0.8.0rc1.dist-info/WHEEL
strangeworks_qiskit_ionq_extension-0.8.0rc1.dist-info/entry_points.txt
strangeworks_qiskit_ionq_extension-0.8.0rc1.dist-info/RECORD
