Metadata-Version: 2.4
Name: strangeworks-qiskit-ionq-extension
Version: 0.8.0rc1
Summary: Add your description here
Author-email: Strange Devs <hello@strangeworks.com>
Requires-Python: >=3.11
Requires-Dist: strangeworks-extensions>=0.7.0
